py_arkose_generator/__init__.py
py_arkose_generator/arkose.py
py_arkose_generator/crypt.py
py_arkose_generator/fingerprint.py
py_arkose_generator/murmur.py
py_arkose_generator/util.py
py_arkose_generator-0.0.0.2.dist-info/METADATA
py_arkose_generator-0.0.0.2.dist-info/WHEEL
py_arkose_generator-0.0.0.2.dist-info/top_level.txt
py_arkose_generator-0.0.0.2.dist-info/RECORD
