Metadata-Version: 2.1
Name: py_arkose_generator
Version: 0.0.0.2
Home-page: https://github.com/Zai-Kun/py-arkose-token-generator/tree/main
Requires-Dist: pycryptodome
Requires-Dist: mmh3
